fastaliyun/__init__.py
fastaliyun/fastaliyun.py
fastaliyun/fastdatahub.py
fastaliyun/fastoss.py
fastaliyun-0.1.8.dist-info/METADATA
fastaliyun-0.1.8.dist-info/WHEEL
fastaliyun-0.1.8.dist-info/top_level.txt
fastaliyun-0.1.8.dist-info/RECORD
