Metadata-Version: 2.4
Name: fastaliyun
Version: 0.1.8
Summary: make it easy to use aliyun sdk
Home-page: https://gitee.com/ZeroSeeker/fastaliyun
Author: ZeroSeeker
Author-email: zeroseeker@foxmail.com
Classifier: Programming Language :: Python :: 3
Classifier: Operating System :: OS Independent
Requires-Dist: envx>=1.0.1
Requires-Dist: pydatahub>=2.18.2
Requires-Dist: showlog>=0.0.6
Requires-Dist: urllib3==1.26.9
Requires-Dist: oss2>=2.15.0
Requires-Dist: fastredis>=0.1.0
Requires-Dist: numpy<=1.23.5
Dynamic: author
Dynamic: author-email
Dynamic: classifier
Dynamic: description
Dynamic: description-content-type
Dynamic: home-page
Dynamic: requires-dist
Dynamic: summary
